{
	"configurations" : 
	[
		{
			"directories" : 
			[
				{
					"build" : ".",
					"jsonFile" : "directory-.-Debug-d0094a50bb2071803777.json",
					"minimumCMakeVersion" : 
					{
						"string" : "3.5"
					},
					"projectIndex" : 0,
					"source" : ".",
					"targetIndexes" : 
					[
						0
					]
				}
			],
			"name" : "Debug",
			"projects" : 
			[
				{
					"directoryIndexes" : 
					[
						0
					],
					"name" : "MyCMakeTemplate",
					"targetIndexes" : 
					[
						0
					]
				}
			],
			"targets" : 
			[
				{
					"directoryIndex" : 0,
					"id" : "MyCMakeTemplate::@6890427a1f51a3e7e1df",
					"jsonFile" : "target-MyCMakeTemplate-Debug-2429a615a401b98e2611.json",
					"name" : "MyCMakeTemplate",
					"projectIndex" : 0
				}
			]
		}
	],
	"kind" : "codemodel",
	"paths" : 
	{
		"build" : "F:/MyGitLib/MyCMakeTemplate/build",
		"source" : "F:/MyGitLib/MyCMakeTemplate"
	},
	"version" : 
	{
		"major" : 2,
		"minor" : 7
	}
}
